WildParse/__init__.py
WildParse/parser.py
WildParse-0.1.2.dist-info/METADATA
WildParse-0.1.2.dist-info/WHEEL
WildParse-0.1.2.dist-info/top_level.txt
WildParse-0.1.2.dist-info/RECORD
