Metadata-Version: 2.1
Name: WildParse
Version: 0.1.2
Summary: это копия одной либы(специально не буду говорить какой), но без надоедливого высера в консоли при запуске(из разряда: ВАШИ ДАННЫЕ ПРИНАДЛЕЖАТ НЕ ВАМ А MICROSOFT, У У У У У Я ТУПАЯ МАКАКА, У У У Я НЕНАВИЖУ ВИНДУ)
Home-page: UNKNOWN
Author: ThunderFoxYT, FBEmpire
Author-email: bulbapotato2.0@gmail.com
License: UNKNOWN
Platform: UNKNOWN
Classifier: Programming Language :: Python :: 3
Classifier: License :: OSI Approved :: MIT License
Classifier: Operating System :: OS Independent
Requires-Python: >=3.6
Requires-Dist: requests>=2.25.1
Requires-Dist: beautifulsoup4>=4.9.3
